backprompt/__init__.py
backprompt/client.py
backprompt/prompt.py
backprompt-0.1.1.dist-info/LICENSE
backprompt-0.1.1.dist-info/METADATA
backprompt-0.1.1.dist-info/WHEEL
backprompt-0.1.1.dist-info/top_level.txt
backprompt-0.1.1.dist-info/RECORD
