Metadata-Version: 2.1
Name: backprompt
Version: 0.1.1
Summary: AI Integration, Simplified. Tailor LLM outputs to your exact needs, no datasets or finetuning required.
Home-page: https://github.com/backprompt-ai/backprompt
Author: Backprompt
Author-email: Backprompt Team <dev@backprompt.ai>
Project-URL: Homepage, https://backprompt.ai
Project-URL: Repository, https://github.com/backprompt-ai/backprompt
Keywords: backprompt,ai,llm,prompt engineering,api
Classifier: License :: OSI Approved :: MIT License
Classifier: Programming Language :: Python
Classifier: Programming Language :: Python :: 3
Requires-Python: >=3.7
License-File: LICENSE
Requires-Dist: httpx>=0.23.0
Provides-Extra: dev
Requires-Dist: pytest; extra == "dev"
